event_store/__init__.py
event_store/domain/__init__.py
event_store/domain/model/event_store.py
event_store/domain/model/event_store_serializer.py
event_store/domain/model/exceptions.py
event_store/domain/model/sequenced_event_store.py
event_store/domain/model/__init__.py
event_store/infrastructure/__init__.py
event_store/infrastructure/configuration/__init__.py
event_store/infrastructure/persistence/in_memory_event_store.py
event_store/infrastructure/persistence/pickle_serializer.py
event_store/infrastructure/persistence/sql_event_store.py
event_store/infrastructure/persistence/__init__.py
event_store/infrastructure/persistence/schema/custom_types.py
event_store/infrastructure/persistence/schema/event_store_schema.py
event_store/infrastructure/persistence/schema/__init__.py
event_store/infrastructure/reflection/reflection.py
event_store/infrastructure/reflection/__init__.py
event_store/infrastructure/scripts/database_tools.py
event_store/infrastructure/scripts/main.py
event_store/infrastructure/scripts/__init__.py
event_store-1.0.1a9.dist-info/DESCRIPTION.rst
event_store-1.0.1a9.dist-info/entry_points.txt
event_store-1.0.1a9.dist-info/METADATA
event_store-1.0.1a9.dist-info/metadata.json
event_store-1.0.1a9.dist-info/RECORD
event_store-1.0.1a9.dist-info/top_level.txt
event_store-1.0.1a9.dist-info/WHEEL
