Metadata-Version: 2.0
Name: event-store
Version: 1.0.1a9
Summary: Event Store implemented in Python
Home-page: https://bitbucket.org/drozdyuk/event-store
Author: Andriy Drozdyuk
Author-email: drozzy@gmail.com
License: Apache 2.0
Keywords: eventstore eventsourcing
Platform: UNKNOWN
Classifier: Development Status :: 3 - Alpha
Classifier: Intended Audience :: Developers
Classifier: Topic :: Software Development :: Libraries
Classifier: License :: OSI Approved :: Apache Software License
Classifier: Programming Language :: Python :: 2
Requires-Dist: sqlalchemy (>=0.9.8)
Requires-Dist: psycopg2 (>=2.5.3)
Provides-Extra: test
Requires-Dist: fake-factory; extra == 'test'
